compute_modules/__init__.py
compute_modules/_version.py
compute_modules/annotations.py
compute_modules/arguments/__init__.py
compute_modules/arguments/arguments.py
compute_modules/auth/__init__.py
compute_modules/auth/pipeline.py
compute_modules/auth/third_party.py
compute_modules/bin/__init__.py
compute_modules/bin/ontology/__init__.py
compute_modules/bin/ontology/_config_path.py
compute_modules/bin/ontology/_types.py
compute_modules/bin/ontology/generate_metadata_config.py
compute_modules/bin/ontology/metadata_client.py
compute_modules/bin/ontology/metadata_loader.py
compute_modules/bin/static_inference/__init__.py
compute_modules/bin/static_inference/infer.py
compute_modules/client/__init__.py
compute_modules/client/encoder.py
compute_modules/client/internal_query_client.py
compute_modules/context/__init__.py
compute_modules/context/context.py
compute_modules/context/types.py
compute_modules/function_registry/__init__.py
compute_modules/function_registry/datetime_conversion_util.py
compute_modules/function_registry/function.py
compute_modules/function_registry/function_payload_converter.py
compute_modules/function_registry/function_registry.py
compute_modules/function_registry/function_schema_parser.py
compute_modules/function_registry/types.py
compute_modules/logging/__init__.py
compute_modules/logging/common.py
compute_modules/logging/internal.py
compute_modules/logging/public.py
compute_modules/py.typed
compute_modules/resources/__init__.py
compute_modules/resources/pipeline_resources.py
compute_modules/resources/types.py
compute_modules/sources/__init__.py
compute_modules/sources/_sources.py
compute_modules/sources_v2/__init__.py
compute_modules/sources_v2/_api.py
compute_modules/sources_v2/_back_compat.py
compute_modules/sources_v2/_sources.py
compute_modules/startup.py
foundry_compute_modules-0.29.0.dist-info/METADATA
foundry_compute_modules-0.29.0.dist-info/WHEEL
foundry_compute_modules-0.29.0.dist-info/entry_points.txt
foundry_compute_modules-0.29.0.dist-info/licenses/LICENSE.txt
foundry_compute_modules-0.29.0.dist-info/RECORD
