Metadata-Version: 2.4
Name: foundry-compute-modules
Version: 0.29.0
Summary: The official Python library for creating Compute Modules
License: Apache-2.0
License-File: LICENSE.txt
Keywords: Palantir,Foundry,Compute Modules
Author: Palantir Technologies, Inc.
Requires-Python: >=3.9,<4.0
Classifier: License :: OSI Approved :: Apache Software License
Classifier: Programming Language :: Python :: 3
Classifier: Programming Language :: Python :: 3.9
Classifier: Programming Language :: Python :: 3.10
Classifier: Programming Language :: Python :: 3.11
Classifier: Programming Language :: Python :: 3.12
Classifier: Programming Language :: Python :: 3.13
Classifier: Programming Language :: Python :: 3.14
Provides-Extra: sources
Requires-Dist: external-systems[sources] (>=0.108.0,<0.109.0) ; extra == "sources"
Requires-Dist: pyyaml (>=6.0.1,<7.0.0) ; extra == "sources"
Requires-Dist: requests (>=2.32.3,<3.0.0)
Project-URL: Repository, https://github.com/palantir/python-compute-module
